dht/__init__.py
dht/bucket_set.py
dht/dht.py
dht/dht_request_handler.py
dht/dht_server.py
dht/peer.py
dht/shortlist.py
dht/storage.py
dht/utils.py
little_bird-0.0.2.dist-info/METADATA
little_bird-0.0.2.dist-info/RECORD
little_bird-0.0.2.dist-info/WHEEL
little_bird-0.0.2.dist-info/top_level.txt
