Metadata-Version: 2.1
Name: little-bird
Version: 0.0.2
Summary: A Python3 Kademlia overlay network implementation. 
Home-page: https://github.com/ZigmundVonZaun/little-bird
Author: ziggs
Author-email: ziggs@airmail.cc
License: UNKNOWN
Platform: UNKNOWN
Classifier: Programming Language :: Python :: 3
Classifier: License :: OSI Approved :: MIT License
Classifier: Operating System :: OS Independent
Requires-Dist: python-dotenv
Requires-Dist: logbook
Requires-Dist: netifaces
